examples/__init__.py
examples/discover_wave.py
examples/run_async.py
examples/run_midi.py
examples/run_threads.py
genki_wave/__init__.py
genki_wave/asyncio_runner.py
genki_wave/callbacks.py
genki_wave/constants.py
genki_wave/discover.py
genki_wave/protocols.py
genki_wave/threading_runner.py
genki_wave/utils.py
genki_wave/data/__init__.py
genki_wave/data/enums.py
genki_wave/data/organization.py
genki_wave/data/points.py
genki_wave/data/structures.py
genki_wave/data/writing.py
genki_wave-0.5.3.dist-info/LICENSE
genki_wave-0.5.3.dist-info/METADATA
genki_wave-0.5.3.dist-info/WHEEL
genki_wave-0.5.3.dist-info/top_level.txt
genki_wave-0.5.3.dist-info/RECORD
