Metadata-Version: 2.1
Name: genki-wave
Version: 0.5.3
Summary: Python API for Wave by Genki
Home-page: https://github.com/genkiinstruments/genki-wave
Author: Robert Torfason
Author-email: robert@genkiinstruments.com
License: MIT
Classifier: Intended Audience :: Developers
Classifier: License :: OSI Approved :: MIT License
Classifier: Operating System :: MacOS :: MacOS X
Classifier: Operating System :: POSIX :: Linux
Classifier: Programming Language :: Python :: 3
Classifier: Programming Language :: Python :: 3.8
Requires-Python: >=3.8
License-File: LICENSE
Requires-Dist: bleak
Requires-Dist: cobs
Requires-Dist: pyserial
Requires-Dist: pyserial-asyncio
